vscode_alt_marketplace/__init__.py
vscode_alt_marketplace/blueprints.py
vscode_alt_marketplace/constants.py
vscode_alt_marketplace/components/__init__.py
vscode_alt_marketplace/components/common.py
vscode_alt_marketplace/components/gallery.py
vscode_alt_marketplace/components/sources.py
vscode_alt_marketplace/examples/__init__.py
vscode_alt_marketplace/examples/cache_gallery.py
vscode_alt_marketplace/examples/local_gallery.py
vscode_alt_marketplace/examples/static/default_icon.png
vscode_alt_marketplace/examples/static/default_icon_128.png
vscode_alt_marketplace/examples/static/vendor/css/bootstrap.min.css
vscode_alt_marketplace/examples/static/vendor/css/font-awesome.all.min.css
vscode_alt_marketplace/examples/static/vendor/js/bootstrap.bundle.min.js
vscode_alt_marketplace/examples/templates/header.html.j2
vscode_alt_marketplace/examples/templates/item.html.j2
vscode_alt_marketplace/examples/templates/landing.html.j2
vscode_alt_marketplace/models/__init__.py
vscode_alt_marketplace/models/gallery.py
vscode_alt_marketplace/models/vsixmanifest.py
vscode_alt_marketplace/utils/__init__.py
vscode_alt_marketplace/utils/extension.py
vscode_alt_marketplace/utils/flask.py
vscode_alt_marketplace/utils/matching.py
vscode_alt_marketplace/utils/misc.py
vscode_alt_marketplace-0.3.2.dist-info/METADATA
vscode_alt_marketplace-0.3.2.dist-info/WHEEL
vscode_alt_marketplace-0.3.2.dist-info/top_level.txt
vscode_alt_marketplace-0.3.2.dist-info/RECORD
